{
    "KPlugin": {
        "Description": "Customize Visual Appearance",
        "Description[ar]": "خصّص المظهر المرئيّ",
        "Description[az]": "Xarici görünüşünü dəyişdirin",
        "Description[bg]": "Настройки на външния вид",
        "Description[ca@valencia]": "Personalitza l'aparença visual",
        "Description[ca]": "Personalitza l'aparença visual",
        "Description[cs]": "Nastavení vzhledu",
        "Description[de]": "Erscheinungsbild anpassen",
        "Description[en_GB]": "Customise Visual Appearance",
        "Description[es]": "Personalizar el aspecto visual",
        "Description[eu]": "Egokitu ikus-itxura norbere gustura",
        "Description[fi]": "Mukauta ulkoasua",
        "Description[fr]": "Personnaliser l'aspect visuel",
        "Description[ia]": "Personalisa le apparentia visual",
        "Description[it]": "Personalizza l'aspetto",
        "Description[ka]": "ვიზუალური გარეგნობის მორგება",
        "Description[ko]": "보이는 모양 사용자 정의",
        "Description[nl]": "Pas het uiterlijk aan",
        "Description[pl]": "Zmiana wyglądu",
        "Description[pt]": "Personalizar a Aparência Visual",
        "Description[pt_BR]": "Personaliza a aparência visual",
        "Description[ru]": "Настройка внешнего вида",
        "Description[sl]": "Prilagodi videz",
        "Description[sv]": "Anpassa visuellt uppträdande",
        "Description[ta]": "தோற்றத்தை மாற்றியமையுங்கள்",
        "Description[tr]": "Görünümü Özelleştir",
        "Description[uk]": "Налаштування зовнішнього вигляду",
        "Description[x-test]": "xxCustomize Visual Appearancexx",
        "Description[zh_CN]": "自定义视觉外观",
        "Icon": "preferences-desktop-theme",
        "Name": "Appearance",
        "Name[af]": "Appearance",
        "Name[ar]": "المظهر",
        "Name[az]": "Xarici görünüş",
        "Name[be]": "Вонкавы выгляд",
        "Name[bg]": "Външен вид",
        "Name[br]": "Neuziadur",
        "Name[bs]": "Izgled",
        "Name[ca@valencia]": "Aparença",
        "Name[ca]": "Aparença",
        "Name[cs]": "Vzhled",
        "Name[cy]": "Golwg",
        "Name[da]": "Udseende",
        "Name[de]": "Erscheinungsbild",
        "Name[el]": "Εμφάνιση",
        "Name[en_GB]": "Appearance",
        "Name[eo]": "Prezentado",
        "Name[es]": "Apariencia",
        "Name[et]": "Välimus",
        "Name[eu]": "Itxura",
        "Name[fa]": "ظاهر",
        "Name[fi]": "Ulkoasu",
        "Name[fr]": "Apparence",
        "Name[fy]": "Uterlik",
        "Name[ga]": "Cuma",
        "Name[gl]": "Aparencia",
        "Name[he]": "מראה",
        "Name[hr]": "Izgled",
        "Name[hu]": "Megjelenés",
        "Name[ia]": "Apparentia",
        "Name[is]": "Útlit",
        "Name[it]": "Aspetto",
        "Name[ja]": "外観",
        "Name[ka]": "გარეგნობა",
        "Name[kk]": "Сыртқы көрінісі",
        "Name[km]": "រូបរាង",
        "Name[ko]": "모양",
        "Name[lt]": "Išvaizda",
        "Name[lv]": "Izskats",
        "Name[mai]": "प्रकटन",
        "Name[mk]": "Изглед",
        "Name[mr]": "दर्शनीयता",
        "Name[ms]": "Rupa",
        "Name[nb]": "Utseende",
        "Name[nds]": "Utsehn",
        "Name[ne]": "देखावट",
        "Name[nl]": "Uiterlijk",
        "Name[nn]": "Utsjånad",
        "Name[pa]": "ਦਿੱਖ",
        "Name[pl]": "Wygląd",
        "Name[pt]": "Aparência",
        "Name[pt_BR]": "Aparência",
        "Name[ro]": "Aspect",
        "Name[ru]": "Внешний вид",
        "Name[se]": "Fárda",
        "Name[sk]": "Vzhľad",
        "Name[sl]": "Videz",
        "Name[sq]": "Paraqitja",
        "Name[sr@ijekavian]": "Изглед",
        "Name[sr@ijekavianlatin]": "Izgled",
        "Name[sr@latin]": "Izgled",
        "Name[sr]": "Изглед",
        "Name[sv]": "Utseende",
        "Name[ta]": "தோற்றம்",
        "Name[tg]": "Намуди зоҳирӣ",
        "Name[th]": "รูปลักษณ์",
        "Name[tr]": "Görünüm",
        "Name[ug]": "كۆرۈنۈشى",
        "Name[uk]": "Вигляд",
        "Name[uz@cyrillic]": "Кўриниши",
        "Name[uz]": "Koʻrinishi",
        "Name[wa]": "Rivnance",
        "Name[x-test]": "xxAppearancexx",
        "Name[zh_CN]": "外观",
        "Name[zh_TW]": "外觀",
        "ServiceTypes": [
            "KCModule"
        ]
    },
    "X-DocPath": "kmail2/index.html#configure-appearance",
    "X-KDE-Weight": 300
}
